{
    "auto": [
        "head",
        "style",
        "script",
        "nav",
        "button",
        "picture",
        "figure",
        "figcaption",
        "svg",
        "aside",
        "noscript"
    ],
    "_generic_": [
        "auto"
    ],
    "bbc.com": [
        "head",
        "style",
        "script",
        "footer",
        "nav",
        "button",
        "picture",
        "figure",
        "figcaption",
        "svg",
        "aside",
        "noscript",
        "div data-component=\"include-html",
        "header header-content",
        "section data-component=\"tag-list",
        "div topic-list",
        "ul list",
        "span visually-hidden",
        "a can-i-share-things-from-the-bbc",
        "div id=\"share-tools-panel",
        "div class=\"ssrcss-13nu8ri-GroupChildren",
        "div spacing=\"2\" class=\"ssrcss-1f3bvyz-Stack",
        "div data-component=\"links-block"
    ],
    "en.antaranews.com": [
        "head",
        "footer",
        "style",
        "script",
        "nav",
        "button",
        "ul",
        "picture",
        "figure",
        "figcaption",
        "svg",
        "noscript",
        "ins",
        "footer class=\"post-meta",
        "footer class=\"footer source-org",
        "div class=\"mt5",
        "div share-",
        "div form-group",
        "div comments",
        "a class=\"navbar",
        "div class=\"footer",
        "div class=\"modal",
        "ul class=\"nav",
        "div post-nav-label",
        "div related-posts",
        "div share-buttons",
        "article widget-post clearfix",
        "div class=\"category",
        "div footer-block",
        "ul footer-menu",
        "div class=\"widget",
        "div mega-menu",
        "li dropdown",
        "h4 entry-title",
        "article news-block small-block",
        "span baca-juga",
        "div wp-caption",
        "div menuscrol",
        "div topdate",
        "div quote_old"
    ],
    "id.antaranews.com": [
        "en.antaranews.com"
    ],
    "news.detik.com": [
        "head",
        "style",
        "script",
        "nav",
        "header",
        "footer",
        "figure",
        "figcaption",
        "svg",
        "noscript",
        "article list-content__item",
        "div detail__share",
        "a video20detik",
        "div lihatjg",
        "a nav__item",
        "a nav",
        "h2 class=\"box",
        "ul class=\"newlist",
        "a dtr-evt=\"box berita",
        "a box pemilu 2024",
        "p id=\"adv-",
        "p id=\"para_caption",
        "div class=\"nav",
        "div dtkframebar",
        "div kat_divide",
        "div id=\"bt_tkt",
        "div class=\"mgr-16",
        "div page__breadcrumb",
        "div box__title",
        "div media__",
        "div sticky-share",
        "div cb-pemilu__desc",
        "div adv-callback",
        "span close_tbot",
        "a dtr-evt=",
        "table linksisip",
        "div detikads"
    ],
    "finance.detik.com": [
        "news.detik.com"
    ],
    "inet.detik.com": [
        "news.detik.com"
    ],
    "hot.detik.com": [
        "news.detik.com"
    ],
    "sport.detik.com": [
        "news.detik.com"
    ],
    "oto.detik.com": [
        "news.detik.com"
    ],
    "travel.detik.com": [
        "news.detik.com"
    ],
    "food.detik.com": [
        "news.detik.com"
    ],
    "health.detik.com": [
        "news.detik.com"
    ],
    "wolipop.detik.com": [
        "news.detik.com"
    ],
    "20.detik.com": [
        "news.detik.com"
    ],
    "foto.detik.com": [
        "news.detik.com"
    ],
    "detik.com": [
        "news.detik.com"
    ],
    "nytimes.com": [
        "head",
        "style",
        "script",
        "nav",
        "button",
        "picture",
        "figure",
        "figcaption",
        "svg",
        "aside",
        "noscript",
        "a href=\"/section/",
        "span css-1n6z4y",
        "section complementary",
        "div bottom-slug",
        "a #after-bottom",
        "a #after-top",
        "a #after-sponsor",
        "div css-pga13o",
        "div css-1bvtpon",
        "a css-kgn7zc",
        "div id=\"sponsor-slug",
        "div id=\"top-slug",
        "span css-x15j1o"
    ],
    "theguardian.com": [
        "head",
        "style",
        "script",
        "nav",
        "button",
        "picture",
        "figure",
        "figcaption",
        "svg",
        "aside",
        "noscript",
        "footer",
        "gu-island",
        "a #maincontent",
        "a #navigation",
        "div dcr-1492oy5",
        "div dcr-bi2aot",
        "div dcr-1gd007l",
        "div dcr-g8r8o3",
        "span dcr-1ppwqv1",
        "ul pillar-list",
        "div data-print-layout",
        "a data-link-name=\"meta-syndication-article",
        "div dcr-u82shn",
        "div dcr-1wf840d",
        "div dcr-ygowzy",
        "a href=\"#top"
    ],
    "okusiassociates.com": [
        "okusiassociates.id"
    ],
    "okusi.id": [
        "okusiassociates.id"
    ],
    "okusiassociates.id": [
        "head",
        "style",
        "script",
        "nav",
        "button",
        "picture",
        "figure",
        "figcaption",
        "svg",
        "aside",
        "noscript",
        "footer"
    ]
 }